asposecellscloud/__init__.py
asposecellscloud/api_client.py
asposecellscloud/configuration.py
asposecellscloud/rest.py
asposecellscloud/apis/__init__.py
asposecellscloud/apis/cells_api.py
asposecellscloud/models/__init__.py
asposecellscloud/models/above_average.py
asposecellscloud/models/abstract_calculation_engine.py
asposecellscloud/models/abstract_calculation_monitor.py
asposecellscloud/models/access_token_response.py
asposecellscloud/models/add_text_options.py
asposecellscloud/models/aggregate_result_by_color.py
asposecellscloud/models/aggregate_result_by_color_response.py
asposecellscloud/models/analyze_excel_request.py
asposecellscloud/models/analyzed_column_description.py
asposecellscloud/models/analyzed_result.py
asposecellscloud/models/analyzed_table_description.py
asposecellscloud/models/applied_operate.py
asposecellscloud/models/applied_step.py
asposecellscloud/models/arc_shape.py
asposecellscloud/models/arc_shape_response.py
asposecellscloud/models/area.py
asposecellscloud/models/auto_filter.py
asposecellscloud/models/auto_filter_response.py
asposecellscloud/models/auto_fitter_options.py
asposecellscloud/models/auto_shape.py
asposecellscloud/models/auto_shape_response.py
asposecellscloud/models/auto_shapes.py
asposecellscloud/models/auto_shapes_response.py
asposecellscloud/models/axis.py
asposecellscloud/models/axis_response.py
asposecellscloud/models/base_operate_options.py
asposecellscloud/models/batch_convert_request.py
asposecellscloud/models/batch_lock_request.py
asposecellscloud/models/batch_protect_request.py
asposecellscloud/models/batch_split_request.py
asposecellscloud/models/border.py
asposecellscloud/models/border_response.py
asposecellscloud/models/broken_link.py
asposecellscloud/models/broken_links_response.py
asposecellscloud/models/button.py
asposecellscloud/models/button_response.py
asposecellscloud/models/calculate_formula_response.py
asposecellscloud/models/calculation_options.py
asposecellscloud/models/cell.py
asposecellscloud-25.12.dist-info/licenses/LICENSE
asposecellscloud-25.12.dist-info/METADATA
asposecellscloud-25.12.dist-info/WHEEL
asposecellscloud-25.12.dist-info/top_level.txt
asposecellscloud-25.12.dist-info/RECORD
