Metadata-Version: 2.4
Name: asposecellscloud
Version: 25.12
Summary: Python Cloud SDK wraps Aspose.Cells REST API so you could seamlessly integrate Microsoft Excel® spreadsheet generation, manipulation, conversion & inspection features into your own Python applications.
Home-page: https://github.com/aspose-cells-cloud/aspose-cells-cloud-python
Author: Aspose Cloud
Author-email: Aspose Cloud <aspose.cloud@aspose.com>
Project-URL: Homepage, https://github.com/aspose-cells-cloud/aspose-cells-cloud-python
Keywords: excel,spreadsheet,convert,xlsx,pdf,json,cloud,rest api,merge,split,protect
Classifier: Programming Language :: Python :: 2.7
Classifier: Programming Language :: Python :: 3.6
Classifier: License :: OSI Approved :: MIT License
Classifier: Operating System :: OS Independent
Requires-Python: >=3.6
License-File: LICENSE
Requires-Dist: urllib3>=1.15
Requires-Dist: six>=1.10
Requires-Dist: certifi
Requires-Dist: python-dateutil
Dynamic: author
Dynamic: home-page
Dynamic: license-file
